axel_lab_to_nwb/__init__.py
axel_lab_to_nwb/conversion_module.py
axel_lab_to_nwb/npz_to_nwb.py
axel_lab_to_nwb/nwb_gui.py
axel_lab_to_nwb-0.1.0.dist-info/LICENSE
axel_lab_to_nwb-0.1.0.dist-info/METADATA
axel_lab_to_nwb-0.1.0.dist-info/WHEEL
axel_lab_to_nwb-0.1.0.dist-info/top_level.txt
axel_lab_to_nwb-0.1.0.dist-info/RECORD
