Metadata-Version: 2.1
Name: axel-lab-to-nwb
Version: 0.1.0
Summary: NWB conversion scripts and tutorials.
Home-page: UNKNOWN
Author: Luiz Tauffer and Ben Dichter
License: UNKNOWN
Platform: UNKNOWN
Requires-Dist: matplotlib
Requires-Dist: cycler
Requires-Dist: scipy
Requires-Dist: numpy
Requires-Dist: jupyter
Requires-Dist: h5py
Requires-Dist: pynwb
Requires-Dist: ndx-grayscalevolume
Requires-Dist: pyyaml
Requires-Dist: skimage
Requires-Dist: seaborn
